LICENSE
MANIFEST.in
README.rst
setup.py
audit_trail/__init__.py
audit_trail/admin.py
audit_trail/apps.py
audit_trail/choices.py
audit_trail/common.py
audit_trail/history.py
audit_trail/middleware.py
audit_trail/models.py
audit_trail/signals.py
audit_trail/views.py
audit_trail/migrations/0001_initial.py
audit_trail/migrations/__init__.py
audit_trail/models/__init__.py
audit_trail/models/content_type.py
audit_trail/models/entity.py
audit_trail/models/field.py
audit_trail/models/fielddiff.py
audit_trail/models/parent_entity_child_field_map.py
audit_trail/models/storage_bin.py
audit_trail/models/xaction.py
audit_trail/models/xaction_parent_entity_child_field_map.py
audit_trail/static/audit_trail/icon-history.png
audit_trail/static/audit_trail/style.css
audit_trail/templates/audit_trail/admin_cl_icon.html
audit_trail/templates/audit_trail/history.html
audit_trail/templatetags/__init__.py
audit_trail/templatetags/extra_tags.py
django_model_audit.egg-info/PKG-INFO
django_model_audit.egg-info/SOURCES.txt
django_model_audit.egg-info/dependency_links.txt
django_model_audit.egg-info/top_level.txt